diydjango
