Metadata-Version: 1.1
Name: diy-django
Version: 1.3.0
Summary: diy-django
Home-page: https://github.com/collinanderson/diy-django
Author: Collin Anderson
Author-email: cmawebsite@gmail.com
License: CC0
Platform: UNKNOWN
Classifier: Development Status :: 5 - Production/Stable
Classifier: Framework :: Django
Classifier: Programming Language :: Python :: 3
